getmodulerely/__init__.py
getmodulerely/__main__.py
getmodulerely-1.0.0.dist-info/LICENSE
getmodulerely-1.0.0.dist-info/METADATA
getmodulerely-1.0.0.dist-info/WHEEL
getmodulerely-1.0.0.dist-info/top_level.txt
getmodulerely-1.0.0.dist-info/RECORD
